<annotation>
	<folder>Sorted dataset</folder>
	<filename>train_00023164.jpg</filename>
	<path>F:\new\darkflow-master\cfg\Sorted dataset\train_00023164.jpg</path>
	<source>
		<database>Unknown</database>
	</source>
	<size>
		<width>252</width>
		<height>253</height>
		<depth>3</depth>
	</size>
	<segmented>0</segmented>
	<object>
		<name>thief</name>
		<pose>Unspecified</pose>
		<truncated>0</truncated>
		<difficult>0</difficult>
		<bndbox>
			<xmin>96</xmin>
			<ymin>20</ymin>
			<xmax>213</xmax>
			<ymax>189</ymax>
		</bndbox>
	</object>
</annotation>
